{
    "name": "Rare Whajje",
    "description": "Inspired by frequent contact with a certain bubble-blowing Seasonal, the Rare one of this Wublin has been reimagined in that Monster's partial likeness. Lagomorph ears and a white and purple striped torso evoke the pre-eminent detective who was instrumental in revealing Electricity's landmark island in the first place - Whajje think about that?",
    "image": "https://github.com/Gaboom63/MSM-API/blob/main/images/bm/Rare Whajje.png?raw=true",
    "cost": "N/A",
    "ascensionCost": "10 Keys",
    "islands": [
        "wublin"
    ],
    "breedingCombo": [
        "N/A"
    ],
    "polarity": [
        "Negative from: Rare Zynth, Negative toward: Rare Pixolotl, Positive from: Rare Dwumrohl, Positive toward: Rare Creepscule"
    ],
    "powerUpTime": [
        "Unlimited."
    ]
}